felloff/__init__.py
felloff/cli.py
felloff/frontmatter.py
felloff/reader.py
felloff/writer.py
felloff-0.1.1.dist-info/METADATA
felloff-0.1.1.dist-info/WHEEL
felloff-0.1.1.dist-info/entry_points.txt
felloff-0.1.1.dist-info/RECORD
