Metadata-Version: 2.4
Name: felloff
Version: 0.1.1
Summary: A library and command-line utility to deal with YAML front matter.
Project-URL: source, https://codeberg.org/scy/felloff
Project-URL: documentation, https://codeberg.org/scy/felloff
Project-URL: issues, https://codeberg.org/scy/felloff/issues
Project-URL: changelog, https://codeberg.org/scy/felloff/src/branch/main/CHANGELOG.md
Author: scy
Maintainer: scy
Classifier: Development Status :: 4 - Beta
Classifier: Environment :: Console
Classifier: License :: OSI Approved :: MIT License
Classifier: Operating System :: POSIX
Classifier: Programming Language :: Python :: 3 :: Only
Classifier: Programming Language :: Python :: 3.10
Classifier: Programming Language :: Python :: 3.11
Classifier: Programming Language :: Python :: 3.12
Classifier: Programming Language :: Python :: 3.13
Classifier: Topic :: File Formats
Classifier: Topic :: Text Processing :: Markup :: Markdown
Classifier: Topic :: Utilities
Requires-Python: <4,>=3.10
Requires-Dist: ruamel-yaml~=0.18
